{"now":1673011243,"now_dt":"2023-01-06T13:20:43.506781Z","info":{"url":"https://yandex.ru/pogoda/120590?lat=59.74044037\u0026lon=30.46816063","lat":59.74044037,"lon":30.46816063},"fact":{"obs_time":1673010000,"temp":-12,"feels_like":-17,"icon":"bkn_n","condition":"cloudy","wind_speed":2,"wind_dir":"sw","pressure_mm":765,"pressure_pa":1019,"humidity":79,"daytime":"n","polar":false,"season":"winter","wind_gust":3.6},"forecast":{"date":"2023-01-06","date_ts":1672952400,"week":1,"sunrise":"09:55","sunset":"16:12","moon_code":0,"moon_text":"moon-code-0","parts":[{"part_name":"evening","temp_min":-13,"temp_avg":-13,"temp_max":-12,"wind_speed":1.6,"wind_gust":4.5,"wind_dir":"nw","pressure_mm":766,"pressure_pa":1021,"humidity":89,"prec_mm":0,"prec_prob":0,"prec_period":240,"icon":"ovc","condition":"overcast","feels_like":-17,"daytime":"n","polar":false},{"part_name":"night","temp_min":-14,"temp_avg":-13,"temp_max":-12,"wind_speed":1.2,"wind_gust":3.5,"wind_dir":"nw","pressure_mm":767,"pressure_pa":1022,"humidity":90,"prec_mm":0,"prec_prob":0,"prec_period":480,"icon":"ovc","condition":"overcast","feels_like":-17,"daytime":"n","polar":false}]}}